pyuno/__init__.py
pyuno/aerial/__init__.py
pyuno/aerial/client/__init__.py
pyuno/aerial/client/config.py
pyuno/aerial/client/feeshare.py
pyuno/aerial/client/urls.py
pyuno/feeshare/__init__.py
pyuno/feeshare/interface.py
pyuno/feeshare/rest_client.py
pyuno/protos/__init__.py
pyuno/protos/confio/__init__.py
pyuno/protos/confio/proofs_pb2.py
pyuno/protos/confio/proofs_pb2_grpc.py
pyuno/protos/cosmos/__init__.py
pyuno/protos/cosmos/auth/__init__.py
pyuno/protos/cosmos/auth/v1beta1/__init__.py
pyuno/protos/cosmos/auth/v1beta1/auth_pb2.py
pyuno/protos/cosmos/auth/v1beta1/auth_pb2_grpc.py
pyuno/protos/cosmos/auth/v1beta1/genesis_pb2.py
pyuno/protos/cosmos/auth/v1beta1/genesis_pb2_grpc.py
pyuno/protos/cosmos/auth/v1beta1/query_pb2.py
pyuno/protos/cosmos/auth/v1beta1/query_pb2_grpc.py
pyuno/protos/cosmos/authz/__init__.py
pyuno/protos/cosmos/authz/v1beta1/__init__.py
pyuno/protos/cosmos/authz/v1beta1/authz_pb2.py
pyuno/protos/cosmos/authz/v1beta1/authz_pb2_grpc.py
pyuno/protos/cosmos/authz/v1beta1/event_pb2.py
pyuno/protos/cosmos/authz/v1beta1/event_pb2_grpc.py
pyuno/protos/cosmos/authz/v1beta1/genesis_pb2.py
pyuno/protos/cosmos/authz/v1beta1/genesis_pb2_grpc.py
pyuno/protos/cosmos/authz/v1beta1/query_pb2.py
pyuno/protos/cosmos/authz/v1beta1/query_pb2_grpc.py
pyuno/protos/cosmos/authz/v1beta1/tx_pb2.py
pyuno/protos/cosmos/authz/v1beta1/tx_pb2_grpc.py
pyuno/protos/cosmos/bank/__init__.py
pyuno/protos/cosmos/bank/v1beta1/__init__.py
pyuno/protos/cosmos/bank/v1beta1/authz_pb2.py
pyuno/protos/cosmos/bank/v1beta1/authz_pb2_grpc.py
pyuno/protos/cosmos/bank/v1beta1/bank_pb2.py
pyuno/protos/cosmos/bank/v1beta1/bank_pb2_grpc.py
pyuno/protos/cosmos/bank/v1beta1/genesis_pb2.py
pyuno/protos/cosmos/bank/v1beta1/genesis_pb2_grpc.py
pyuno/protos/cosmos/bank/v1beta1/query_pb2.py
pyuno/protos/cosmos/bank/v1beta1/query_pb2_grpc.py
pyuno/protos/cosmos/bank/v1beta1/tx_pb2.py
pyuno/protos/cosmos/bank/v1beta1/tx_pb2_grpc.py
pyuno/protos/cosmos/base/__init__.py
pyuno-0.1.2.dist-info/LICENSE
pyuno-0.1.2.dist-info/METADATA
pyuno-0.1.2.dist-info/WHEEL
pyuno-0.1.2.dist-info/RECORD
