Metadata-Version: 2.1
Name: pyuno
Version: 0.1.2
Summary: 
Author: Kleomedes Dev Team
Requires-Python: >=3.8,<4.0
Classifier: Programming Language :: Python :: 3
Classifier: Programming Language :: Python :: 3.8
Classifier: Programming Language :: Python :: 3.9
Classifier: Programming Language :: Python :: 3.10
Classifier: Programming Language :: Python :: 3.11
Requires-Dist: cosmpy (==0.9.0)
